calcdict/__init__.py
calcdict-1.0.1.dist-info/LICENSE.txt
calcdict-1.0.1.dist-info/METADATA
calcdict-1.0.1.dist-info/WHEEL
calcdict-1.0.1.dist-info/top_level.txt
calcdict-1.0.1.dist-info/RECORD
