Metadata-Version: 2.1
Name: calcdict
Version: 1.0.1
Summary: Calculate values only when needed.
Author-email: Johannes <johannes-programming@posteo.org>
License: The MIT License (MIT)
Project-URL: Download, https://pypi.org/project/calcdict/#files
Project-URL: Source, https://github.com/johannes-programming/calcdict
Classifier: License :: OSI Approved :: MIT License
Classifier: Programming Language :: Python
Classifier: Programming Language :: Python :: 3
Requires-Python: >=3.11
License-File: LICENSE.txt
